[
    {
        "program_id": "CTDT2021",
        "cohort": 2021,
        "name": "Chương trình đào tạo đại học khóa 2021",
        "program_types": [
            "CQUI",
            "CNTN"
        ],
        "majors": [
            {
                "major_id": "KHDL",
                "major_name": "Khoa học dữ liệu",
                "training_credits": 121,
                "required_courses": [
                    "SS003",
                    "SS007",
                    "SS008",
                    "SS009",
                    "SS010",
                    "MA006",
                    "MA003",
                    "MA004",
                    "MA005",
                    "IT001",
                    "ENG01",
                    "ENG02",
                    "ENG03",
                    "PE012",
                    "ME001",
                    "SS004",
                    "SS006",
                    "IT002",
                    "IT003",
                    "IT004",
                    "IT005",
                    "IT010",
                    "IT007",
                    "DS005",
                    "DS101",
                    "DS105",
                    "IS211",
                    "DS102",
                    "DS103",
                    "DS200",
                    "DS201",
                    "DS204",
                    "DS104",
                    "DS106",
                    "DS300",
                    "DS302",
                    "DS303",
                    "DS304",
                    "IS353",
                    "DS310",
                    "NT532",
                    "DS301",
                    "DS306",
                    "DS307",
                    "DS305",
                    "DS308",
                    "IS217",
                    "SE104",
                    "CS221",
                    "IE207",
                    "DS505"
                ],
                "progress_details": {
                    "required_general_education": 45,
                    "required_major_core": 12,
                    "required_major_foundation": 40,
                    "required_graduation_project": 12,
                    "required_elective_credits": 12
                }
            },
            {
                "major_id": "TMDT",
                "major_name": "Thương mại điện tử",
                "training_credits": 126,
                "required_courses": [
                    "SS003",
                    "SS007",
                    "SS008",
                    "SS009",
                    "SS010",
                    "MA006",
                    "MA003",
                    "MA004",
                    "MA005",
                    "ENG01",
                    "ENG02",
                    "ENG03",
                    "PE012",
                    "ME001",
                    "SS004",
                    "SS006",
                    "IT001",
                    "IT002",
                    "IT003",
                    "IT004",
                    "IT005",
                    "EC005",
                    "SE104",
                    "EC001",
                    "EC003",
                    "EC201",
                    "IS334",
                    "IS207",
                    "EC311",
                    "EC312",
                    "EC213",
                    "EC337",
                    "EC208",
                    "EC229",
                    "EC335",
                    "EC214",
                    "EC331",
                    "EC332",
                    "EC333",
                    "EC334",
                    "EC338",
                    "EC336",
                    "EC002",
                    "IS210",
                    "NT118",
                    "IS336",
                    "IS217",
                    "IS405",
                    "IS403",
                    "IS353",
                    "IS105",
                    "IS332",
                    "EC232",
                    "IS254",
                    "IS252"
                ],
                "progress_details": {
                    "required_general_education": 41,
                    "required_major_core": 23,
                    "required_major_foundation": 43,
                    "required_graduation_project": 12,
                    "required_elective_credits": 7
                }
            },
            {
                "major_id": "ATTT",
                "major_name": "An toàn thông tin",
                "training_credits": 131,
                "required_courses": [
                    "SS003",
                    "SS007",
                    "SS008",
                    "SS009",
                    "SS010",
                    "SS006",
                    "MA003",
                    "MA004",
                    "MA005",
                    "MA006",
                    "PH001",
                    "PH002",
                    "IT001",
                    "SS004",
                    "IT002",
                    "IT003",
                    "IT004",
                    "IT005",
                    "IT006",
                    "IT007",
                    "NT015",
                    "NT106",
                    "NT101",
                    "NT230",
                    "NT132",
                    "NT219",
                    "NT209",
                    "NT114",
                    "NT204",
                    "NT330",
                    "NT207",
                    "NT137",
                    "NT213",
                    "NT334",
                    "NT532",
                    "NT535",
                    "NT211",
                    "NT212",
                    "NT534",
                    "NT133",
                    "NT521",
                    "NT522",
                    "NT523",
                    "NT215",
                    "NT505",
                    "NT131",
                    "NT208",
                    "NT205"
                ],
                "progress_details": {
                    "required_general_education": 52,
                    "required_major_core": 9,
                    "required_major_foundation": 46,
                    "required_graduation_project": 12,
                    "required_elective_credits": 12
                }
            },
            {
                "major_id": "MMTT",
                "major_name": "Mạng máy tính và truyền thông dữ liệu",
                "training_credits": 136,
                "required_courses": [
                    "SS003",
                    "SS007",
                    "SS008",
                    "SS009",
                    "SS010",
                    "MA006",
                    "MA003",
                    "MA004",
                    "MA005",
                    "PH001",
                    "PH002",
                    "IT001",
                    "ENG01",
                    "ENG02",
                    "ENG03",
                    "PE012",
                    "ME001",
                    "SS004",
                    "SS006",
                    "IT002",
                    "IT003",
                    "IT004",
                    "IT005",
                    "IT006",
                    "IT007",
                    "NT005",
                    "NT101",
                    "NT131",
                    "NT105",
                    "NT106",
                    "NT118",
                    "NT132",
                    "NT113",
                    "NT531",
                    "NT532",
                    "NT533",
                    "NT536",
                    "NT402",
                    "NT538",
                    "NT210",
                    "NT333",
                    "NT334",
                    "NT205",
                    "NT330",
                    "NT207",
                    "NT534",
                    "NT535",
                    "NT103",
                    "NT208",
                    "NT201",
                    "NT209",
                    "NT104",
                    "NT109",
                    "NT303",
                    "NT331",
                    "NT204",
                    "NT537",
                    "NT114",
                    "NT215",
                    "NT505",
                    "NT332",
                    "NT539",
                    "NT405",
                    "NT121"
                ],
                "progress_details": {
                    "required_general_education": 52,
                    "required_major_core": 12,
                    "required_major_foundation": 49,
                    "required_graduation_project": 14,
                    "required_elective_credits": 9
                }
            },
            {
                "major_id": "KTMT",
                "major_name": "Kỹ thuật máy tính",
                "training_credits": 126,
                "required_courses": [
                    "SS003",
                    "SS006",
                    "SS007",
                    "SS008",
                    "SS009",
                    "SS010",
                    "PE012",
                    "ME001",
                    "ENG01",
                    "ENG02",
                    "ENG03",
                    "MA006",
                    "MA003",
                    "MA004",
                    "MA005",
                    "PH002",
                    "IT001",
                    "IT002",
                    "IT003",
                    "IT004",
                    "IT005",
                    "IT006",
                    "IT007",
                    "CE005",
                    "CE103",
                    "CE118",
                    "CE119",
                    "CE121",
                    "CE124",
                    "CE213",
                    "CE224",
                    "CE222",
                    "SS004",
                    "CE201",
                    "CE206",
                    "CE502",
                    "CE505",
                    "CE334",
                    "CE433",
                    "CE409",
                    "CE232",
                    "CE339",
                    "CE344",
                    "CE410",
                    "CE408",
                    "CE412"
                ],
                "progress_details": {
                    "required_general_education": 49,
                    "required_major_core": 8,
                    "required_major_foundation": 49,
                    "required_graduation_project": 16,
                    "required_elective_credits": 4
                }
            },
            {
                "major_id": "KTPM",
                "major_name": "Kỹ thuật phần mềm",
                "training_credits": 136,
                "required_courses": [
                    "SS003",
                    "SS007",
                    "SS008",
                    "SS009",
                    "SS010",
                    "MA006",
                    "MA003",
                    "MA004",
                    "MA005",
                    "IT001",
                    "ENG01",
                    "ENG02",
                    "ENG03",
                    "PE012",
                    "ME001",
                    "SS004",
                    "SS006",
                    "IT002",
                    "IT003",
                    "IT004",
                    "IT005",
                    "IT007",
                    "SE005",
                    "IT012",
                    "IT008",
                    "SE104",
                    "SE100",
                    "SE101",
                    "SE102",
                    "SE114",
                    "SE106",
                    "SE214",
                    "SE301",
                    "SE215",
                    "SE113",
                    "SE358",
                    "SE330",
                    "SE402",
                    "SE332",
                    "SE334",
                    "CS519",
                    "SE347",
                    "SE350",
                    "SE351",
                    "SE343",
                    "SE355",
                    "SE310",
                    "SE346",
                    "SE404",
                    "SE331",
                    "IE202",
                    "IE406",
                    "IS341",
                    "IS252",
                    "IS254",
                    "IS405",
                    "IS353",
                    "SE313",
                    "SE352",
                    "SE109",
                    "SE354",
                    "IS201",
                    "SE356",
                    "SE357",
                    "SE325",
                    "SE221",
                    "SE220",
                    "SE320",
                    "SE327",
                    "SE328",
                    "SE344",
                    "SE329",
                    "SE121",
                    "SE122",
                    "SE400",
                    "SE401",
                    "SE403",
                    "SE405"
                ],
                "progress_details": {
                    "required_general_education": 45,
                    "required_major_core": 12,
                    "required_major_foundation": 51,
                    "required_graduation_project": 16,
                    "required_elective_credits": 12
                }
            },
            {
                "major_id": "KHMT",
                "major_name": "Khoa học máy tính",
                "training_credits": 126,
                "required_courses": [
                    "SS003",
                    "SS007",
                    "SS008",
                    "SS009",
                    "SS010",
                    "MA006",
                    "MA003",
                    "MA004",
                    "MA005",
                    "IT001",
                    "ENG01",
                    "ENG02",
                    "ENG03",
                    "PE012",
                    "ME001",
                    "SS004",
                    "SS006",
                    "IT002",
                    "IT003",
                    "IT004",
                    "IT005",
                    "IT010",
                    "IT007",
                    "IS005",
                    "IS220",
                    "IS201",
                    "IS210",
                    "IS208",
                    "IS216",
                    "IS336",
                    "IS207",
                    "NT118",
                    "IS211",
                    "IS252",
                    "IS217",
                    "IS403",
                    "NT532",
                    "IS232",
                    "IS254",
                    "IS334",
                    "IS332",
                    "IS351",
                    "IS352",
                    "IS251",
                    "IS335",
                    "IS339",
                    "EC202",
                    "EC331",
                    "IS502",
                    "IS401",
                    "IS402",
                    "IS405",
                    "IS353"
                ],
                "progress_details": {
                    "required_general_education": 45,
                    "required_major_core": 16,
                    "required_major_foundation": 45,
                    "required_graduation_project": 12,
                    "required_elective_credits": 8
                }
            },
            {
                "major_id": "HTTT",
                "major_name": "Hệ thống thông tin",
                "training_credits": 140,
                "required_courses": [
                    "SS003",
                    "SS006",
                    "SS007",
                    "SS008",
                    "SS009",
                    "SS010",
                    "MA003",
                    "MA004",
                    "MA005",
                    "MA006",
                    "IT001",
                    "ENG01",
                    "ENG02",
                    "ENG03",
                    "PExxx",
                    "ME001",
                    "SS004",
                    "CS115",
                    "IT002",
                    "SE104",
                    "CS111",
                    "CS526",
                    "CS311",
                    "CS116",
                    "IT003",
                    "CS112",
                    "CS117",
                    "CS523",
                    "IT012",
                    "IT007",
                    "IT005",
                    "IT004",
                    "CS005",
                    "CS217",
                    "CS214",
                    "CS211",
                    "CS312",
                    "CS313",
                    "CS314",
                    "CS315",
                    "CS316",
                    "CS106",
                    "CS114",
                    "CS221",
                    "CS229",
                    "CS226",
                    "CS222",
                    "CS323",
                    "CS324",
                    "CS321",
                    "CS325",
                    "CS231",
                    "CS105",
                    "CS331",
                    "CS532",
                    "CS338",
                    "CS333",
                    "CS336",
                    "CS337",
                    "CS535",
                    "CS232",
                    "CS519",
                    "CS529",
                    "CS551",
                    "CS332",
                    "CS527",
                    "CS528",
                    "CS505",
                    "CS409",
                    "CS405",
                    "CS406",
                    "CS410",
                    "CS419",
                    "CS412",
                    "CS420",
                    "CS431"
                ],
                "progress_details": {
                    "required_general_education": 45,
                    "required_major_core": 8,
                    "required_major_foundation": 68,
                    "required_graduation_project": 12,
                    "required_elective_credits": 7
                }
            },
            {
                "major_id": "CNTT",
                "major_name": "Công nghệ thông tin",
                "training_credits": 125,
                "required_courses": [
                    "SS003",
                    "SS007",
                    "SS008",
                    "SS009",
                    "SS010",
                    "MA006",
                    "MA003",
                    "MA004",
                    "MA005",
                    "IT001",
                    "ENG01",
                    "ENG02",
                    "ENG03",
                    "PE012",
                    "ME001",
                    "SS004",
                    "SS006",
                    "IT002",
                    "IT003",
                    "IT004",
                    "IT005",
                    "IT012",
                    "IT007",
                    "IE005",
                    "IE101",
                    "IE103",
                    "IE104",
                    "IE105",
                    "IE106",
                    "SE104",
                    "IS402",
                    "IE201",
                    "IE212",
                    "IS217",
                    "IS254",
                    "IE221",
                    "IE224",
                    "IE309",
                    "IE202",
                    "IE203",
                    "IS208",
                    "IS336",
                    "IE301",
                    "IE302",
                    "IE102",
                    "IE204",
                    "IE213",
                    "IS353",
                    "IS334",
                    "IE303",
                    "IE307",
                    "IS251",
                    "IS352",
                    "IS351",
                    "IE205",
                    "IE304",
                    "IE305",
                    "IE207",
                    "IE505",
                    "IE401",
                    "IE402",
                    "IE403",
                    "IE405",
                    "IE406"
                ],
                "progress_details": {
                    "required_general_education": 45,
                    "required_major_core": 12,
                    "required_major_foundation": 44,
                    "required_graduation_project": 12,
                    "required_elective_credits": 12
                }
            }
        ]
    },
    {
        "program_id": "CTDT2022",
        "cohort": 2022,
        "name": "Chương trình đào tạo đại học khóa 2022",
        "program_types": [
            "CQUI",
            "CNTN"
        ],
        "majors": [
            {
                "major_id": "KHDL",
                "major_name": "Khoa học dữ liệu",
                "training_credits": 123,
                "required_courses": [
                    "DS005",
                    "IT002",
                    "IT003",
                    "IT004",
                    "IT005",
                    "IT010",
                    "IT007",
                    "DS107",
                    "DS101",
                    "DS105",
                    "DS102",
                    "DS108",
                    "DS304",
                    "DS307",
                    "DS200",
                    "DS104",
                    "DS204",
                    "DS201",
                    "DS310",
                    "DS106",
                    "IE107",
                    "IE104",
                    "BUS1125",
                    "DS311",
                    "DS309",
                    "DS207",
                    "DS505",
                    "DS300",
                    "DS301",
                    "DS306",
                    "DS305",
                    "DS302",
                    "DS303",
                    "DS308",
                    "IE403"
                ],
                "progress_details": {
                    "required_general_education": 45,
                    "required_major_core": 14,
                    "required_major_foundation": 42,
                    "required_graduation_project": 12,
                    "required_elective_credits": 10
                }
            },
            {
                "major_id": "TMDT",
                "major_name": "Thương mại điện tử",
                "training_credits": 125,
                "required_courses": [
                    "SS003",
                    "SS007",
                    "SS008",
                    "SS009",
                    "SS010",
                    "SS006",
                    "MA006",
                    "MA003",
                    "MA004",
                    "MA005",
                    "IT001",
                    "ENG01",
                    "ENG02",
                    "ENG03",
                    "PE012",
                    "ME001",
                    "SS004",
                    "IT002",
                    "IT003",
                    "IT004",
                    "IT005",
                    "EC005",
                    "EC001",
                    "EC101",
                    "EC201",
                    "IS334",
                    "IS207",
                    "EC204",
                    "EC312",
                    "EC213",
                    "EC337",
                    "EC208",
                    "EC229",
                    "EC335",
                    "IS336",
                    "EC214",
                    "EC232",
                    "EC333",
                    "EC338",
                    "EC002",
                    "EC304",
                    "EC222",
                    "EC401",
                    "EC331",
                    "EC402",
                    "EC403",
                    "IS403",
                    "IS355"
                ],
                "progress_details": {
                    "required_general_education": 45,
                    "required_major_core": 24,
                    "required_major_foundation": 35,
                    "required_graduation_project": 12,
                    "required_elective_credits": 9
                }
            },
            {
                "major_id": "ATTT",
                "major_name": "An toàn thông tin",
                "training_credits": 129,
                "required_courses": [
                    "SS003",
                    "SS007",
                    "SS008",
                    "SS009",
                    "SS010",
                    "SS006",
                    "MA003",
                    "MA004",
                    "MA005",
                    "MA006",
                    "PH001",
                    "PH002",
                    "IT001",
                    "SS004",
                    "IT002",
                    "IT003",
                    "IT004",
                    "IT005",
                    "IT006",
                    "IT007",
                    "NT015",
                    "NT106",
                    "NT101",
                    "NT230",
                    "NT132",
                    "NT219",
                    "NT209",
                    "NT114",
                    "NT204",
                    "NT330",
                    "NT207",
                    "NT137",
                    "NT213",
                    "NT334",
                    "NT532",
                    "NT535",
                    "NT211",
                    "NT212",
                    "NT534",
                    "NT133",
                    "NT521",
                    "NT522",
                    "NT523",
                    "NT215",
                    "NT505",
                    "NT131",
                    "NT208",
                    "NT205"
                ],
                "progress_details": {
                    "required_general_education": 49,
                    "required_major_core": 9,
                    "required_major_foundation": 51,
                    "required_graduation_project": 14,
                    "required_elective_credits": 6
                }
            },
            {
                "major_id": "MMTT",
                "major_name": "Mạng máy tính và truyền thông dữ liệu",
                "training_credits": 136,
                "required_courses": [
                    "SS003",
                    "SS006",
                    "SS007",
                    "SS008",
                    "SS009",
                    "SS010",
                    "MA006",
                    "MA003",
                    "MA004",
                    "MA005",
                    "PH002",
                    "IT001",
                    "ENG01",
                    "ENG02",
                    "ENG03",
                    "ME001",
                    "PE012",
                    "IT002",
                    "IT003",
                    "IT004",
                    "IT005",
                    "IT006",
                    "IT007",
                    "NT005",
                    "NT101",
                    "NT131",
                    "NT105",
                    "NT106",
                    "NT118",
                    "NT132",
                    "NT113",
                    "NT531",
                    "NT532",
                    "NT533",
                    "NT536",
                    "NT402",
                    "NT538",
                    "NT540",
                    "NT541",
                    "NT542",
                    "NT543",
                    "NT209",
                    "SS004",
                    "NT210",
                    "NT334",
                    "NT205",
                    "NT330",
                    "NT207",
                    "NT534",
                    "NT405",
                    "NT208",
                    "NT201",
                    "NT109",
                    "NT204",
                    "NT121",
                    "NT114",
                    "NT215",
                    "NT505",
                    "NT332",
                    "NT539",
                    "NT535",
                    "NT544",
                    "NT545",
                    "NT546"
                ],
                "progress_details": {
                    "required_general_education": 49,
                    "required_major_core": 12,
                    "required_major_foundation": 49,
                    "required_graduation_project": 12,
                    "required_elective_credits": 6
                }
            },
            {
                "major_id": "KTMT",
                "major_name": "Kỹ thuật máy tính",
                "training_credits": 128,
                "required_courses": [
                    "SS003",
                    "SS006",
                    "SS007",
                    "SS008",
                    "SS009",
                    "SS010",
                    "MA006",
                    "MA003",
                    "MA004",
                    "MA005",
                    "PH002",
                    "IT001",
                    "ENG01",
                    "ENG02",
                    "ENG03",
                    "ME001",
                    "PE001",
                    "PE002",
                    "IT002",
                    "IT003",
                    "IT004",
                    "IT005",
                    "IT006",
                    "IT007",
                    "CE005",
                    "CE103",
                    "CE118",
                    "CE119",
                    "CE121",
                    "CE124",
                    "CE213",
                    "CE224",
                    "SS004",
                    "CE502",
                    "CE201",
                    "CE206",
                    "CE505",
                    "CE410",
                    "CE408",
                    "CE410",
                    "CE412",
                    "CE410",
                    "CE412",
                    "CE433",
                    "CE222",
                    "CE334",
                    "CE332",
                    "CE436",
                    "CE410",
                    "CE434",
                    "CE435",
                    "CE232",
                    "CE406",
                    "CE339",
                    "CE340",
                    "CE342",
                    "CE3031",
                    "CE437",
                    "CE438",
                    "CE212",
                    "CE23x",
                    "CE341",
                    "CE440",
                    "CE441",
                    "CE442"
                ],
                "progress_details": {
                    "required_general_education": 49,
                    "required_major_core": 8,
                    "required_major_foundation": 49,
                    "required_graduation_project": 16,
                    "required_elective_credits": 6
                }
            },
            {
                "major_id": "KTPM",
                "major_name": "Kỹ thuật phần mềm",
                "training_credits": 130,
                "required_courses": [
                    "SS003",
                    "SS007",
                    "SS008",
                    "SS009",
                    "SS010",
                    "SS006",
                    "MA006",
                    "MA003",
                    "MA004",
                    "MA005",
                    "IT001",
                    "ENG01",
                    "ENG02",
                    "ENG03",
                    "ME001",
                    "PE012",
                    "IT002",
                    "IT003",
                    "IT004",
                    "IT005",
                    "IT007",
                    "SE005",
                    "IT012",
                    "IT008",
                    "SE104",
                    "SE100",
                    "SE101",
                    "SE102",
                    "SE114",
                    "SE106",
                    "SE214",
                    "SE301",
                    "SE215",
                    "SE113",
                    "SE358",
                    "SE330",
                    "SE332",
                    "SE334",
                    "SE347",
                    "SE350",
                    "SE351",
                    "SE343",
                    "SE355",
                    "SE310",
                    "SE346",
                    "SE404",
                    "SE331",
                    "SE313",
                    "SE352",
                    "SE109",
                    "SE356",
                    "SE357",
                    "SE325",
                    "SE221",
                    "SE220",
                    "SE320",
                    "SE327",
                    "SE328",
                    "SE344",
                    "SE329",
                    "SS004",
                    "SE501",
                    "SE121",
                    "SE122",
                    "SE505",
                    "SE400",
                    "SE401",
                    "SE403",
                    "SE405"
                ],
                "progress_details": {
                    "required_general_education": 45,
                    "required_major_core": 14,
                    "required_major_foundation": 49,
                    "required_graduation_project": 16,
                    "required_elective_credits": 6
                }
            },
            {
                "major_id": "KHMT",
                "major_name": "Khoa học máy tính",
                "training_credits": 126,
                "required_courses": [
                    "SS003",
                    "SS006",
                    "SS007",
                    "SS008",
                    "SS009",
                    "SS010",
                    "MA003",
                    "MA004",
                    "MA005",
                    "MA006",
                    "IT001",
                    "ENG01",
                    "ENG02",
                    "ENG03",
                    "PE012",
                    "ME001",
                    "SS004",
                    "CS115",
                    "IT002",
                    "SE104",
                    "CS111",
                    "CS526",
                    "CS311",
                    "CS116",
                    "IT003",
                    "CS112",
                    "CS117",
                    "CS523",
                    "IT012",
                    "IT007",
                    "IT005",
                    "IT004",
                    "CS005",
                    "CS217",
                    "CS214",
                    "CS211",
                    "CS312",
                    "CS313",
                    "CS314",
                    "CS315",
                    "CS316",
                    "CS106",
                    "CS114",
                    "CS221",
                    "CS229",
                    "CS226",
                    "CS222",
                    "CS323",
                    "CS324",
                    "CS321",
                    "CS325",
                    "CS231",
                    "CS105",
                    "CS331",
                    "CS532",
                    "CS338",
                    "CS333",
                    "CS336",
                    "CS337",
                    "CS535",
                    "CS232",
                    "CS519",
                    "CS529",
                    "CS551",
                    "CS332",
                    "CS527",
                    "CS528",
                    "CS505",
                    "CS409",
                    "CS405",
                    "CS406",
                    "CS410",
                    "CS419",
                    "CS412",
                    "CS420",
                    "CS431"
                ],
                "progress_details": {
                    "required_general_education": 45,
                    "required_major_core": 16,
                    "required_major_foundation": 45,
                    "required_graduation_project": 12,
                    "required_elective_credits": 8
                }
            },
            {
                "major_id": "TTNT",
                "major_name": "Trí tuệ nhân tạo",
                "training_credits": 128,
                "required_courses": [
                    "SS003",
                    "SS006",
                    "SS007",
                    "SS008",
                    "SS009",
                    "SS010",
                    "MA003",
                    "MA004",
                    "MA005",
                    "MA006",
                    "CS115",
                    "ENG01",
                    "ENG02",
                    "ENG03",
                    "PExxx",
                    "ME001",
                    "SS004",
                    "IT001",
                    "IT002",
                    "SE104",
                    "CS111",
                    "CS311",
                    "CS116",
                    "IT003",
                    "CS112",
                    "IT012",
                    "IT007",
                    "IT005",
                    "IT004",
                    "CS106",
                    "CS114",
                    "AI002",
                    "CS221",
                    "CS231",
                    "CS214",
                    "CS232",
                    "AI001",
                    "CS211",
                    "CS315",
                    "CS410",
                    "CS431",
                    "CS217",
                    "CS214",
                    "CS316",
                    "CS312",
                    "CS229",
                    "CS226",
                    "CS222",
                    "CS323",
                    "CS321",
                    "CS325",
                    "CS331",
                    "CS532",
                    "CS338",
                    "CS313",
                    "CS336",
                    "CS535",
                    "DS102",
                    "DS103",
                    "DS200",
                    "DS201",
                    "CE340",
                    "CE344",
                    "IS211",
                    "IS403",
                    "SE113",
                    "SE357",
                    "SE358",
                    "NT538",
                    "NT539",
                    "CS519",
                    "CS529",
                    "CS333",
                    "CS527",
                    "CS523",
                    "CS551",
                    "CS505",
                    "CS409",
                    "CS405",
                    "CS406",
                    "CS419",
                    "CS412"
                ],
                "progress_details": {
                    "required_general_education": 45,
                    "required_major_core": 8,
                    "required_major_foundation": 57,
                    "required_graduation_project": 12,
                    "required_elective_credits": 8
                }
            },
            {
                "major_id": "HTTT",
                "major_name": "Hệ thống thông tin",
                "training_credits": 132,
                "required_courses": [
                    "SS003",
                    "SS007",
                    "SS008",
                    "SS009",
                    "SS010",
                    "MA006",
                    "MA003",
                    "MA004",
                    "MA005",
                    "IT001",
                    "ENG01",
                    "ENG02",
                    "ENG03",
                    "PE012",
                    "ME001",
                    "SS004",
                    "SS006",
                    "IT002",
                    "IT003",
                    "IT004",
                    "IT005",
                    "IT010",
                    "IT007",
                    "IS005",
                    "IS336",
                    "IS201",
                    "IS210",
                    "IS208",
                    "IS216",
                    "IS207",
                    "NT118",
                    "IS211",
                    "IS405",
                    "IS252",
                    "IS217",
                    "IS403",
                    "IS354",
                    "IS356",
                    "IS357",
                    "IS232",
                    "IS254",
                    "IS334",
                    "IS351",
                    "IS251",
                    "IS335",
                    "IS339",
                    "IS220",
                    "NT532",
                    "DS102",
                    "EC213",
                    "EC214",
                    "EC331",
                    "IS502",
                    "IS401",
                    "IS402",
                    "IS353",
                    "IS355"
                ],
                "progress_details": {
                    "required_general_education": 45,
                    "required_major_core": 22,
                    "required_major_foundation": 46,
                    "required_graduation_project": 12,
                    "required_elective_credits": 7
                }
            },
            {
                "major_id": "CNTT",
                "major_name": "Công nghệ thông tin",
                "training_credits": 125,
                "required_courses": [
                    "SS003",
                    "SS007",
                    "SS008",
                    "SS009",
                    "SS010",
                    "MA006",
                    "MA003",
                    "MA004",
                    "MA005",
                    "IT001",
                    "ENG01",
                    "ENG02",
                    "ENG03",
                    "PE012",
                    "ME001",
                    "SS004",
                    "SS006",
                    "IT002",
                    "IT003",
                    "IT004",
                    "IT005",
                    "IT012",
                    "IT007",
                    "IE005",
                    "IE101",
                    "IE103",
                    "IE104",
                    "IE105",
                    "IE106",
                    "IE108",
                    "IS402",
                    "IE201",
                    "IE212",
                    "IS217",
                    "IS254",
                    "IE221",
                    "IE224",
                    "IE309",
                    "BUS1125",
                    "IE202",
                    "IE203",
                    "IS208",
                    "IS336",
                    "IE301",
                    "IE302",
                    "IE102",
                    "IE204",
                    "IE213",
                    "IS353",
                    "IS334",
                    "IE303",
                    "IE307",
                    "IS251",
                    "IS352",
                    "IS351",
                    "IE205",
                    "IE304",
                    "IE305",
                    "IE207",
                    "IE505",
                    "IE401",
                    "IE402",
                    "IE403",
                    "IE405",
                    "IE406"
                ],
                "progress_details": {
                    "required_general_education": 45,
                    "required_major_core": 12,
                    "required_major_foundation": 44,
                    "required_graduation_project": 12,
                    "required_elective_credits": 12
                }
            }
        ]
    },
    {
        "program_id": "CTDT2023",
        "cohort": 2023,
        "name": "Chương trình đào tạo đại học khóa 2023",
        "program_types": [
            "CQUI",
            "CNTN"
        ],
        "majors": [
            {
                "major_id": "KHDL",
                "major_name": "Khoa học dữ liệu",
                "training_credits": 123,
                "required_courses": [
                    "SS003",
                    "SS007",
                    "SS008",
                    "SS009",
                    "SS010",
                    "SS006",
                    "MA006",
                    "MA003",
                    "MA004",
                    "MA005",
                    "IT001",
                    "ENG01",
                    "ENG02",
                    "ENG03",
                    "PE231",
                    "PE232",
                    "ME001",
                    "SS004",
                    "DS005",
                    "IT002",
                    "IT003",
                    "IT004",
                    "IT005",
                    "IT010",
                    "IT007",
                    "DS107",
                    "DS101",
                    "DS105",
                    "DS102",
                    "DS108",
                    "DS304",
                    "DS307",
                    "DS200",
                    "DS315",
                    "IE224",
                    "DS104",
                    "DS317",
                    "DS316",
                    "DS318",
                    "DS204",
                    "DS201",
                    "DS310",
                    "DS106",
                    "DS312",
                    "DS313",
                    "DS314",
                    "DS316",
                    "DS318",
                    "DS204",
                    "IE108",
                    "IE104",
                    "DS311",
                    "IE310",
                    "IE103",
                    "DS309",
                    "BUS1125",
                    "TLH025",
                    "CS231",
                    "CS331",
                    "CS412",
                    "IS353",
                    "CS323",
                    "CS321",
                    "CS410",
                    "CS112",
                    "CS116",
                    "CS115",
                    "CS406",
                    "DS207",
                    "DS505",
                    "DS300",
                    "DS301",
                    "DS306",
                    "DS305",
                    "DS302",
                    "DS303",
                    "DS308",
                    "IE403",
                    "IT009",
                    "IS211",
                    "IE207",
                    "PE012"
                ],
                "progress_details": {
                    "required_general_education": 45,
                    "required_major_core": 18,
                    "required_major_foundation": 42,
                    "required_graduation_project": 12,
                    "required_elective_credits": 6
                }
            },
            {
                "major_id": "TMDT",
                "major_name": "Thương mại điện tử",
                "training_credits": 125,
                "required_courses": [
                    "SS003",
                    "SS007",
                    "SS008",
                    "SS009",
                    "SS010",
                    "SS006",
                    "MA006",
                    "MA003",
                    "MA004",
                    "MA005",
                    "IT001",
                    "ENG01",
                    "ENG02",
                    "ENG03",
                    "PE231",
                    "PE232",
                    "ME001",
                    "SS004",
                    "IT002",
                    "IT003",
                    "IT004",
                    "IT005",
                    "EC005",
                    "EC001",
                    "EC101",
                    "EC201",
                    "IS334",
                    "IS207",
                    "EC204",
                    "EC312",
                    "EC213",
                    "EC337",
                    "EC208",
                    "EC229",
                    "EC335",
                    "IS336",
                    "EC214",
                    "EC232",
                    "EC333",
                    "EC338",
                    "EC002",
                    "EC304",
                    "EC222",
                    "EC401",
                    "EC331",
                    "EC402",
                    "EC403",
                    "IS403",
                    "IS355"
                ],
                "progress_details": {
                    "required_general_education": 45,
                    "required_major_core": 24,
                    "required_major_foundation": 35,
                    "required_graduation_project": 12,
                    "required_elective_credits": 9
                }
            },
            {
                "major_id": "ATTT",
                "major_name": "An toàn thông tin",
                "training_credits": 129,
                "required_courses": [
                    "SS003",
                    "SS006",
                    "SS007",
                    "SS008",
                    "SS009",
                    "SS010",
                    "MA006",
                    "MA003",
                    "MA004",
                    "MA005",
                    "PH002",
                    "IT001",
                    "ENG01",
                    "ENG02",
                    "ENG03",
                    "ME001",
                    "PE231",
                    "PE232",
                    "IT002",
                    "IT003",
                    "IT004",
                    "IT005",
                    "IT006",
                    "IT007",
                    "NT015",
                    "NT106",
                    "NT140",
                    "NT230",
                    "NT132",
                    "NT219",
                    "NT209",
                    "NT208",
                    "NT521",
                    "NT204",
                    "NT330",
                    "NT207",
                    "NT137",
                    "NT213",
                    "NT334",
                    "NT535",
                    "NT211",
                    "NT212",
                    "NT534",
                    "NT133",
                    "NT523",
                    "NT205",
                    "NT547",
                    "NT118",
                    "SS004",
                    "NT114",
                    "NT215",
                    "NT505",
                    "NT541",
                    "NT533",
                    "NT522"
                ],
                "progress_details": {
                    "required_general_education": 49,
                    "required_major_core": 9,
                    "required_major_foundation": 51,
                    "required_graduation_project": 14,
                    "required_elective_credits": 6
                }
            },
            {
                "major_id": "MMTT",
                "major_name": "Mạng máy tính và truyền thông dữ liệu",
                "training_credits": 130,
                "required_courses": [
                    "SS003",
                    "SS006",
                    "SS007",
                    "SS008",
                    "SS009",
                    "SS010",
                    "MA006",
                    "MA003",
                    "MA004",
                    "MA005",
                    "PH002",
                    "IT001",
                    "ENG01",
                    "ENG02",
                    "ENG03",
                    "ME001",
                    "PE231",
                    "PE232",
                    "IT002",
                    "IT003",
                    "IT004",
                    "IT005",
                    "IT006",
                    "IT007",
                    "NT005",
                    "NT101",
                    "NT131",
                    "NT105",
                    "NT106",
                    "NT118",
                    "NT132",
                    "NT113",
                    "NT531",
                    "NT532",
                    "NT533",
                    "NT536",
                    "NT402",
                    "NT538",
                    "NT540",
                    "NT541",
                    "NT542",
                    "NT543",
                    "NT209",
                    "SS004",
                    "NT210",
                    "NT334",
                    "NT205",
                    "NT330",
                    "NT207",
                    "NT534",
                    "NT405",
                    "NT208",
                    "NT201",
                    "NT109",
                    "NT204",
                    "NT121",
                    "NT114",
                    "NT215",
                    "NT505",
                    "NT332",
                    "NT539",
                    "NT535",
                    "NT544",
                    "NT545",
                    "NT546"
                ],
                "progress_details": {
                    "required_general_education": 49,
                    "required_major_core": 12,
                    "required_major_foundation": 49,
                    "required_graduation_project": 14,
                    "required_elective_credits": 6
                }
            },
            {
                "major_id": "KTMT",
                "major_name": "Kỹ thuật máy tính",
                "training_credits": 128,
                "required_courses": [
                    "SS003",
                    "SS006",
                    "SS007",
                    "SS008",
                    "SS009",
                    "SS010",
                    "MA006",
                    "MA003",
                    "MA004",
                    "MA005",
                    "PH002",
                    "IT001",
                    "ENG01",
                    "ENG02",
                    "ENG03",
                    "ME001",
                    "PE231",
                    "PE232",
                    "IT002",
                    "IT003",
                    "IT004",
                    "IT005",
                    "IT006",
                    "IT007",
                    "CE005",
                    "CE103",
                    "CE118",
                    "CE119",
                    "CE122",
                    "CE124",
                    "CE213",
                    "CE224",
                    "CE201",
                    "CE206",
                    "SS004",
                    "CE502",
                    "CE505",
                    "CE410",
                    "CE408",
                    "CE412",
                    "CE413",
                    "CE433",
                    "CE222",
                    "CE334",
                    "CE332",
                    "CE436",
                    "CE434",
                    "CE435",
                    "CE232",
                    "CE439",
                    "CE339",
                    "CE340",
                    "CE342",
                    "CE3031",
                    "CE437",
                    "CE438",
                    "CE212",
                    "CE233",
                    "CE347",
                    "CE440",
                    "CE320",
                    "CE406",
                    "CE441",
                    "CE442"
                ],
                "progress_details": {
                    "required_general_education": 49,
                    "required_major_core": 8,
                    "required_major_foundation": 49,
                    "required_graduation_project": 16,
                    "required_elective_credits": 6
                }
            },
            {
                "major_id": "KTPM",
                "major_name": "Kỹ thuật phần mềm",
                "training_credits": 130,
                "required_courses": [
                    "SS003",
                    "SS007",
                    "SS008",
                    "SS009",
                    "SS010",
                    "SS006",
                    "MA006",
                    "MA003",
                    "MA004",
                    "MA005",
                    "IT001",
                    "ENG01",
                    "ENG02",
                    "ENG03",
                    "IT002",
                    "IT003",
                    "IT004",
                    "IT005",
                    "IT007",
                    "SE005",
                    "IT012",
                    "IT008",
                    "SE104",
                    "SE100",
                    "SE101",
                    "SE102",
                    "SE114",
                    "SE106",
                    "SE214",
                    "SE301",
                    "SE215",
                    "SE113",
                    "SE358",
                    "SE330",
                    "SE332",
                    "SE334",
                    "SE347",
                    "SE350",
                    "SE351",
                    "SE343",
                    "SE355",
                    "SE310",
                    "SE346",
                    "SE404",
                    "SE331",
                    "SE313",
                    "SE352",
                    "SE109",
                    "SE356",
                    "SE357",
                    "SE325",
                    "SE221",
                    "SE220",
                    "SE320",
                    "SE327",
                    "SE328",
                    "SE344",
                    "SE329",
                    "SS004",
                    "SE501",
                    "SE121",
                    "SE122",
                    "SE505",
                    "SE400",
                    "SE401",
                    "SE403",
                    "SE405"
                ],
                "progress_details": {
                    "required_general_education": 45,
                    "required_major_core": 14,
                    "required_major_foundation": 49,
                    "required_graduation_project": 16,
                    "required_elective_credits": 6
                }
            },
            {
                "major_id": "KHMT",
                "major_name": "Khoa học máy tính",
                "training_credits": 126,
                "required_courses": [
                    "SS003",
                    "SS006",
                    "SS007",
                    "SS008",
                    "SS009",
                    "SS010",
                    "MA003",
                    "MA004",
                    "MA005",
                    "MA006",
                    "IT001",
                    "ENG01",
                    "ENG02",
                    "ENG03",
                    "PE231",
                    "PE232",
                    "ME001",
                    "SS004",
                    "CS115",
                    "IT002",
                    "SE104",
                    "CS111",
                    "CS526",
                    "CS311",
                    "CS116",
                    "IT003",
                    "CS112",
                    "CS117",
                    "CS523",
                    "IT012",
                    "IT007",
                    "IT005",
                    "IT004",
                    "CS005",
                    "CS217",
                    "CS214",
                    "CS211",
                    "CS312",
                    "CS313",
                    "CS314",
                    "CS315",
                    "CS316",
                    "CS106",
                    "CS114",
                    "CS221",
                    "CS229",
                    "CS226",
                    "CS222",
                    "CS323",
                    "CS324",
                    "CS321",
                    "CS325",
                    "CS231",
                    "CS105",
                    "CS331",
                    "CS532",
                    "CS338",
                    "CS333",
                    "CS336",
                    "CS337",
                    "CS535",
                    "CS232",
                    "CS519",
                    "CS529",
                    "CS551",
                    "CS332",
                    "CS527",
                    "CS528",
                    "CS505"
                ],
                "progress_details": {
                    "required_general_education": 45,
                    "required_major_core": 16,
                    "required_major_foundation": 45,
                    "required_graduation_project": 12,
                    "required_elective_credits": 8
                }
            },
            {
                "major_id": "TTNT",
                "major_name": "Trí tuệ nhân tạo",
                "training_credits": 128,
                "required_courses": [
                    "SS003",
                    "SS006",
                    "SS007",
                    "SS008",
                    "SS009",
                    "SS010",
                    "MA003",
                    "MA004",
                    "MA005",
                    "MA006",
                    "CS115",
                    "ENG01",
                    "ENG02",
                    "ENG03",
                    "PE012",
                    "ME001",
                    "SS004",
                    "IT001",
                    "IT002",
                    "SE104",
                    "CS111",
                    "CS311",
                    "CS116",
                    "IT003",
                    "CS112",
                    "IT012",
                    "IT007",
                    "IT005",
                    "IT004",
                    "CS106",
                    "CS114",
                    "AI002",
                    "CS221",
                    "CS231",
                    "CS214",
                    "CS232",
                    "AI001",
                    "CS211",
                    "CS315",
                    "CS410",
                    "CS431",
                    "CS217",
                    "CS316",
                    "CS312",
                    "CS229",
                    "CS226",
                    "CS222",
                    "CS323",
                    "CS321",
                    "CS325",
                    "CS331",
                    "CS532",
                    "CS338",
                    "CS313",
                    "CS336",
                    "CS337",
                    "CS535",
                    "AI301",
                    "AI302",
                    "DS102",
                    "DS103",
                    "DS200",
                    "DS201",
                    "CE340",
                    "CE344",
                    "IS211",
                    "IS403",
                    "SE113",
                    "SE357",
                    "SE358",
                    "NT538",
                    "NT539",
                    "CS519",
                    "CS529",
                    "CS333",
                    "CS527",
                    "CS523",
                    "CS551",
                    "AI505",
                    "CS409",
                    "CS405",
                    "CS406",
                    "CS419",
                    "CS412"
                ],
                "progress_details": {
                    "required_general_education": 45,
                    "required_major_core": 8,
                    "required_major_foundation": 57,
                    "required_graduation_project": 12,
                    "required_elective_credits": 8
                }
            },
            {
                "major_id": "HTTT",
                "major_name": "Hệ thống thông tin",
                "training_credits": 132,
                "required_courses": [
                    "SS003",
                    "SS007",
                    "SS008",
                    "SS009",
                    "SS010",
                    "MA006",
                    "MA003",
                    "MA004",
                    "MA005",
                    "IT001",
                    "ENG01",
                    "ENG02",
                    "ENG03",
                    "PE231",
                    "PE232",
                    "ME001",
                    "SS004",
                    "SS006",
                    "IT002",
                    "IT003",
                    "IT004",
                    "IT005",
                    "IT010",
                    "IT007",
                    "IS005",
                    "IS336",
                    "IS201",
                    "IS210",
                    "IS208",
                    "IS216",
                    "IS207",
                    "NT118",
                    "IS211",
                    "IS405",
                    "IS252",
                    "IS217",
                    "IS403",
                    "IS344",
                    "IS346",
                    "IS348",
                    "IS349",
                    "IS360",
                    "IS361",
                    "IS362",
                    "IS345",
                    "IS347",
                    "IS350",
                    "IS354",
                    "IS356",
                    "IS357",
                    "IS232",
                    "IS254",
                    "IS334",
                    "IS351",
                    "IS251",
                    "IS335",
                    "IS339",
                    "IS220",
                    "NT532",
                    "DS102",
                    "EC213",
                    "EC214",
                    "EC331",
                    "IS363",
                    "IS358",
                    "IS364",
                    "IS502",
                    "IS401",
                    "IS402",
                    "IS355",
                    "IS353",
                    "IS406",
                    "IS359"
                ],
                "progress_details": {
                    "required_general_education": 45,
                    "required_major_core": 22,
                    "required_major_foundation": 46,
                    "required_graduation_project": 12,
                    "required_elective_credits": 7
                }
            },
            {
                "major_id": "CNTT",
                "major_name": "Công nghệ thông tin",
                "training_credits": 125,
                "required_courses": [
                    "SS003",
                    "SS007",
                    "SS008",
                    "SS009",
                    "SS010",
                    "SS006",
                    "MA006",
                    "MA003",
                    "MA004",
                    "MA005",
                    "IT001",
                    "ENG01",
                    "ENG02",
                    "ENG03",
                    "PE231",
                    "PE232",
                    "ME001",
                    "SS004",
                    "IT002",
                    "IT003",
                    "IT004",
                    "IT005",
                    "IT012",
                    "IT007",
                    "IE005",
                    "IE101",
                    "IE103",
                    "IE104",
                    "IE105",
                    "IE106",
                    "IE108",
                    "IS402",
                    "IE201",
                    "IE212",
                    "IS217",
                    "IS254",
                    "IE221",
                    "IE224",
                    "IE309",
                    "BUS1125",
                    "IE231",
                    "IE203",
                    "IS208",
                    "IS336",
                    "IE301",
                    "IE302",
                    "IE102",
                    "IE204",
                    "IE213",
                    "IS353",
                    "IS334",
                    "IE303",
                    "IE307",
                    "IS251",
                    "IS352",
                    "IS351",
                    "IE205",
                    "IE304",
                    "IE305",
                    "TLH025",
                    "IE310",
                    "IE207",
                    "IE505",
                    "IE401",
                    "IE402",
                    "IE403",
                    "IE405",
                    "IE406"
                ],
                "progress_details": {
                    "required_general_education": 45,
                    "required_major_core": 18,
                    "required_major_foundation": 44,
                    "required_graduation_project": 12,
                    "required_elective_credits": 6
                }
            }
        ]
    },
    {
        "program_id": "CTDT2024",
        "cohort": 2024,
        "name": "Chương trình đào tạo đại học khóa 2024",
        "program_types": [
            "CQUI",
            "CNTN"
        ],
        "majors": [
            {
                "major_id": "KHDL",
                "major_name": "Khoa học dữ liệu",
                "training_credits": 123,
                "required_courses": [
                    "SS003",
                    "SS007",
                    "SS008",
                    "SS009",
                    "SS010",
                    "SS006",
                    "MA006",
                    "MA003",
                    "MA004",
                    "MA005",
                    "IT001",
                    "ENG01",
                    "ENG02",
                    "ENG03",
                    "PE231",
                    "PE232",
                    "ME001",
                    "SS004",
                    "DS005",
                    "IT002",
                    "IT003",
                    "IT004",
                    "IT005",
                    "IT010",
                    "IT007",
                    "DS107",
                    "DS101",
                    "DS111",
                    "DS102",
                    "DS108",
                    "DS304",
                    "DS307",
                    "DS200",
                    "DS315",
                    "DS325",
                    "DS104",
                    "DS317",
                    "DS322",
                    "DS318",
                    "DS306",
                    "DS305",
                    "IE403",
                    "DS204",
                    "DS207",
                    "DS201",
                    "DS310",
                    "DS106",
                    "DS312",
                    "DS313",
                    "DS314",
                    "DS327",
                    "DS319",
                    "DS320",
                    "DS321",
                    "DS324",
                    "DS300",
                    "DS326",
                    "DS302",
                    "DS303",
                    "DS308",
                    "IE103",
                    "IE108",
                    "IE104",
                    "DS311",
                    "DS323",
                    "IE310",
                    "DS309",
                    "INI01",
                    "BUS1125",
                    "TLH025",
                    "CS231",
                    "CS331",
                    "CS412",
                    "IE233",
                    "CS323",
                    "CS321",
                    "CS410",
                    "CS112",
                    "CS116",
                    "CS115",
                    "CS406",
                    "DS505",
                    "DS400",
                    "DS501"
                ],
                "progress_details": {
                    "required_general_education": 45,
                    "required_major_core": 20,
                    "required_major_foundation": 42,
                    "required_graduation_project": 10,
                    "required_elective_credits": 6
                }
            },
            {
                "major_id": "TMDT",
                "major_name": "Thương mại điện tử",
                "training_credits": 125,
                "required_courses": [
                    "SS003",
                    "SS007",
                    "SS008",
                    "SS009",
                    "SS010",
                    "SS006",
                    "MA006",
                    "MA003",
                    "MA004",
                    "MA005",
                    "IT001",
                    "ENG01",
                    "ENG02",
                    "ENG03",
                    "PE231",
                    "PE232",
                    "ME001",
                    "SS004",
                    "IT002",
                    "IT003",
                    "IT004",
                    "IT005",
                    "EC005",
                    "EC001",
                    "EC101",
                    "EC201",
                    "IS334",
                    "IS207",
                    "EC204",
                    "EC312",
                    "EC213",
                    "EC337",
                    "EC208",
                    "EC229",
                    "EC335",
                    "IS336",
                    "EC214",
                    "EC232",
                    "EC333",
                    "EC338",
                    "EC002",
                    "EC304",
                    "EC222",
                    "EC401",
                    "EC331",
                    "EC402",
                    "EC403",
                    "IS403",
                    "IS355"
                ],
                "progress_details": {
                    "required_general_education": 45,
                    "required_major_core": 24,
                    "required_major_foundation": 35,
                    "required_graduation_project": 12,
                    "required_elective_credits": 9
                }
            },
            {
                "major_id": "ATTT",
                "major_name": "An toàn thông tin",
                "training_credits": 129,
                "required_courses": [
                    "SS003",
                    "SS006",
                    "SS007",
                    "SS008",
                    "SS009",
                    "SS010",
                    "MA006",
                    "MA003",
                    "MA004",
                    "MA005",
                    "PH002",
                    "IT001",
                    "ENG01",
                    "ENG02",
                    "ENG03",
                    "ME001",
                    "PE231",
                    "PE232",
                    "IT002",
                    "IT003",
                    "IT004",
                    "IT005",
                    "IT006",
                    "IT007",
                    "NT015",
                    "NT106",
                    "NT140",
                    "NT230",
                    "NT132",
                    "NT219",
                    "NT209",
                    "NT208",
                    "NT521",
                    "NT204",
                    "NT330",
                    "NT207",
                    "NT137",
                    "NT213",
                    "NT334",
                    "NT535",
                    "NT211",
                    "NT212",
                    "NT534",
                    "NT133",
                    "NT523",
                    "NT205",
                    "NT547",
                    "NT118",
                    "NT522",
                    "SS004",
                    "NT114",
                    "NT215",
                    "NT505",
                    "NT506",
                    "NT508",
                    "NT541",
                    "NT548"
                ],
                "progress_details": {
                    "required_general_education": 49,
                    "required_major_core": 9,
                    "required_major_foundation": 51,
                    "required_graduation_project": 14,
                    "required_elective_credits": 6
                }
            },
            {
                "major_id": "MMTT",
                "major_name": "Mạng máy tính và truyền thông dữ liệu",
                "training_credits": 130,
                "required_courses": [
                    "SS003",
                    "SS006",
                    "SS007",
                    "SS008",
                    "SS009",
                    "SS010",
                    "MA006",
                    "MA003",
                    "MA004",
                    "MA005",
                    "PH002",
                    "IT001",
                    "ENG01",
                    "ENG02",
                    "ENG03",
                    "ME001",
                    "PE231",
                    "PE232",
                    "IT002",
                    "IT003",
                    "IT004",
                    "IT005",
                    "IT006",
                    "IT007",
                    "NT005",
                    "NT101",
                    "NT131",
                    "NT105",
                    "NT106",
                    "NT118",
                    "NT132",
                    "NT113",
                    "NT531",
                    "NT532",
                    "NT533",
                    "NT536",
                    "NT402",
                    "NT538",
                    "NT540",
                    "NT542",
                    "NT543",
                    "NT535",
                    "NT545",
                    "NT546",
                    "NT209",
                    "SS004",
                    "NT210",
                    "NT334",
                    "NT205",
                    "NT330",
                    "NT207",
                    "NT534",
                    "NT405",
                    "NT208",
                    "NT201",
                    "NT109",
                    "NT204",
                    "NT121",
                    "NT114",
                    "NT215",
                    "NT505",
                    "NT506",
                    "NT508",
                    "NT332",
                    "NT539",
                    "NT541",
                    "NT544",
                    "NT548"
                ],
                "progress_details": {
                    "required_general_education": 49,
                    "required_major_core": 12,
                    "required_major_foundation": 49,
                    "required_graduation_project": 14,
                    "required_elective_credits": 6
                }
            },
            {
                "major_id": "KTMT",
                "major_name": "Kỹ thuật máy tính",
                "training_credits": 128,
                "required_courses": [
                    "SS003",
                    "SS006",
                    "SS007",
                    "SS008",
                    "SS009",
                    "SS010",
                    "MA006",
                    "MA003",
                    "MA004",
                    "MA005",
                    "PH002",
                    "IT001",
                    "ENG01",
                    "ENG02",
                    "ENG03",
                    "ME001",
                    "PE231",
                    "PE232",
                    "IT002",
                    "IT003",
                    "IT004",
                    "IT005",
                    "IT006",
                    "IT007",
                    "CE005",
                    "CE103",
                    "CE118",
                    "CE119",
                    "CE122",
                    "CE124",
                    "CE212",
                    "CE224",
                    "CE201",
                    "CE206",
                    "CE232",
                    "CE439",
                    "CE339",
                    "CE340",
                    "CE410",
                    "CE342",
                    "CE348",
                    "CE437",
                    "CE438",
                    "CE233",
                    "CE347",
                    "CE440",
                    "CE320",
                    "CE406",
                    "CE441",
                    "CE442",
                    "SS004",
                    "INI01",
                    "CE502",
                    "CE505",
                    "CE507",
                    "CE508",
                    "CE510",
                    "CE511"
                ],
                "progress_details": {
                    "required_general_education": 49,
                    "required_major_core": 8,
                    "required_major_foundation": 49,
                    "required_graduation_project": 16,
                    "required_elective_credits": 6
                }
            },
            {
                "major_id": "KTPM",
                "major_name": "Kỹ thuật phần mềm",
                "training_credits": 130,
                "required_courses": [
                    "SS003",
                    "SS007",
                    "SS008",
                    "SS009",
                    "SS010",
                    "SS006",
                    "MA006",
                    "MA003",
                    "MA004",
                    "MA005",
                    "IT001",
                    "ENG01",
                    "ENG02",
                    "ENG03",
                    "ME001",
                    "PE231",
                    "PE232",
                    "IT002",
                    "IT003",
                    "IT004",
                    "IT005",
                    "IT007",
                    "SE005",
                    "IT012",
                    "IT008",
                    "SE104",
                    "SE100",
                    "SE101",
                    "SE102",
                    "SE114",
                    "SE106",
                    "SE214",
                    "SE301",
                    "SE215",
                    "SE113",
                    "SE358",
                    "SE330",
                    "SE332",
                    "SE334",
                    "SE347",
                    "SE350",
                    "SE351",
                    "SE343",
                    "SE355",
                    "SE310",
                    "SE346",
                    "SE404",
                    "SE331",
                    "SE313",
                    "SE352",
                    "SE109",
                    "SE356",
                    "SE357",
                    "SE325",
                    "SE221",
                    "SE220",
                    "SE320",
                    "SE327",
                    "SE328",
                    "SE344",
                    "SE329",
                    "SS004",
                    "INI01",
                    "SE501",
                    "SE121",
                    "SE122",
                    "SE505",
                    "SE506",
                    "SE507",
                    "SE400",
                    "SE406",
                    "SE403",
                    "SE407"
                ],
                "progress_details": {
                    "required_general_education": 45,
                    "required_major_core": 14,
                    "required_major_foundation": 49,
                    "required_graduation_project": 16,
                    "required_elective_credits": 6
                }
            },
            {
                "major_id": "KHMT",
                "major_name": "Khoa học máy tính",
                "training_credits": 126,
                "required_courses": [
                    "SS003",
                    "SS006",
                    "SS007",
                    "SS008",
                    "SS009",
                    "SS010",
                    "MA003",
                    "MA004",
                    "MA005",
                    "MA006",
                    "IT001",
                    "ENG01",
                    "ENG02",
                    "ENG03",
                    "PE231",
                    "PE232",
                    "ME001",
                    "SS004",
                    "CS115",
                    "IT002",
                    "SE104",
                    "CS111",
                    "CS526",
                    "CS311",
                    "CS116",
                    "IT003",
                    "CS112",
                    "CS117",
                    "CS523",
                    "IT012",
                    "IT007",
                    "IT005",
                    "IT004",
                    "CS005",
                    "CS217",
                    "CS214",
                    "CS211",
                    "CS312",
                    "CS313",
                    "CS314",
                    "CS315",
                    "CS316",
                    "CS106",
                    "CS114",
                    "CS221",
                    "CS229",
                    "CS226",
                    "CS222",
                    "CS323",
                    "CS324",
                    "CS321",
                    "CS325",
                    "CS231",
                    "CS105",
                    "CS331",
                    "CS532",
                    "CS338",
                    "CS333",
                    "CS336",
                    "CS337",
                    "CS535",
                    "CS232",
                    "CS317",
                    "CS519",
                    "CS529",
                    "CS551",
                    "CS332",
                    "CS333",
                    "CS527",
                    "CS528",
                    "CS505",
                    "CS554",
                    "CS553",
                    "CS409",
                    "CS405",
                    "CS406",
                    "CS410",
                    "CS419",
                    "CS412",
                    "CS420",
                    "CS431"
                ],
                "progress_details": {
                    "required_general_education": 45,
                    "required_major_core": 16,
                    "required_major_foundation": 45,
                    "required_graduation_project": 12,
                    "required_elective_credits": 8
                }
            },
            {
                "major_id": "TTNT",
                "major_name": "Trí tuệ nhân tạo",
                "training_credits": 128,
                "required_courses": [
                    "SS003",
                    "SS006",
                    "SS007",
                    "SS008",
                    "SS009",
                    "SS010",
                    "MA003",
                    "MA004",
                    "MA005",
                    "MA006",
                    "CS115",
                    "ENG01",
                    "ENG02",
                    "ENG03",
                    "PE012",
                    "ME001",
                    "SS004",
                    "IT001",
                    "IT002",
                    "SE104",
                    "CS111",
                    "CS311",
                    "CS116",
                    "IT003",
                    "CS112",
                    "IT012",
                    "IT007",
                    "IT005",
                    "IT004",
                    "CS106",
                    "CS114",
                    "AI002",
                    "CS221",
                    "CS231",
                    "CS214",
                    "CS232",
                    "AI001",
                    "CS211",
                    "CS315",
                    "CS410",
                    "CS431",
                    "CS217",
                    "CS316",
                    "CS312",
                    "CS229",
                    "CS226",
                    "CS222",
                    "CS323",
                    "CS321",
                    "CS325",
                    "CS331",
                    "CS532",
                    "CS338",
                    "CS313",
                    "CS336",
                    "CS337",
                    "CS535",
                    "AI301",
                    "AI302",
                    "DS102",
                    "DS103",
                    "DS200",
                    "DS201",
                    "CE340",
                    "CE344",
                    "IS211",
                    "IS403",
                    "SE113",
                    "SE357",
                    "SE358",
                    "NT538",
                    "NT539",
                    "CS519",
                    "CS529",
                    "CS333",
                    "CS527",
                    "CS523",
                    "CS551",
                    "AI505",
                    "CS409",
                    "CS405",
                    "CS406",
                    "CS419",
                    "CS412"
                ],
                "progress_details": {
                    "required_general_education": 45,
                    "required_major_core": 8,
                    "required_major_foundation": 57,
                    "required_graduation_project": 12,
                    "required_elective_credits": 8
                }
            },
            {
                "major_id": "HTTT",
                "major_name": "Hệ thống thông tin",
                "training_credits": 132,
                "required_courses": [
                    "SS003",
                    "SS007",
                    "SS008",
                    "SS009",
                    "SS010",
                    "MA006",
                    "MA003",
                    "MA004",
                    "MA005",
                    "IT001",
                    "ENG01",
                    "ENG02",
                    "ENG03",
                    "PE231",
                    "PE232",
                    "ME001",
                    "SS004",
                    "SS006",
                    "IT002",
                    "IT003",
                    "IT004",
                    "IT005",
                    "IT010",
                    "IT007",
                    "IS005",
                    "IS336",
                    "IS201",
                    "IS210",
                    "IS208",
                    "IS216",
                    "IS207",
                    "NT118",
                    "IS211",
                    "IS405",
                    "IS252",
                    "IS217",
                    "IS403",
                    "IS344",
                    "IS346",
                    "IS348",
                    "IS349",
                    "IS360",
                    "IS361",
                    "IS362",
                    "IS345",
                    "IS347",
                    "DS312",
                    "IS354",
                    "IS356",
                    "IS357",
                    "IS232",
                    "IS254",
                    "IS334",
                    "IS351",
                    "IS251",
                    "IS335",
                    "IS339",
                    "IS220",
                    "NT532",
                    "DS102",
                    "EC213",
                    "EC214",
                    "EC331",
                    "IS363",
                    "IS358",
                    "IS364",
                    "IS502",
                    "IS401",
                    "IS407",
                    "IS503",
                    "IS402",
                    "IS355",
                    "IS353",
                    "IS406"
                ],
                "progress_details": {
                    "required_general_education": 45,
                    "required_major_core": 22,
                    "required_major_foundation": 46,
                    "required_graduation_project": 12,
                    "required_elective_credits": 7
                }
            },
            {
                "major_id": "CNTT",
                "major_name": "Công nghệ thông tin",
                "training_credits": 125,
                "required_courses": [
                    "SS003",
                    "SS007",
                    "SS008",
                    "SS009",
                    "SS010",
                    "SS006",
                    "MA006",
                    "MA003",
                    "MA004",
                    "MA005",
                    "IT001",
                    "ENG01",
                    "ENG02",
                    "ENG03",
                    "SS004",
                    "IE005",
                    "IT002",
                    "IT003",
                    "IT004",
                    "IT005",
                    "IT012",
                    "IT007",
                    "IE101",
                    "IE103",
                    "IE104",
                    "IE105",
                    "IE106",
                    "IE108",
                    "IE213",
                    "IE307",
                    "IE233",
                    "IE403",
                    "DS300",
                    "IE203",
                    "IE204",
                    "IE303",
                    "IE310",
                    "IE301",
                    "DS322",
                    "IE201",
                    "IE221",
                    "DS108",
                    "IE313",
                    "IE212",
                    "IE302",
                    "IE402",
                    "DS307",
                    "DS317",
                    "IE102",
                    "IE231",
                    "BUS1125",
                    "TLH025",
                    "INI01",
                    "IE207",
                    "IE309",
                    "DS323",
                    "SE113",
                    "NT212",
                    "NT213",
                    "IE505",
                    "IE400",
                    "IE501",
                    "IE502"
                ],
                "progress_details": {
                    "required_general_education": 45,
                    "required_major_core": 18,
                    "required_major_foundation": 44,
                    "required_graduation_project": 12,
                    "required_elective_credits": 6
                }
            },
            {
                "major_id": "TKVM",
                "major_name": "Thiết kế vi mạch",
                "training_credits": 132,
                "required_courses": [
                    "SS003",
                    "SS006",
                    "SS007",
                    "SS008",
                    "SS009",
                    "SS010",
                    "MA006",
                    "MA003",
                    "MA004",
                    "MA005",
                    "PH002",
                    "IT001",
                    "IT003",
                    "IT006",
                    "ENG01",
                    "ENG02",
                    "ENG03",
                    "ME001",
                    "PE231",
                    "PE232",
                    "CE006",
                    "CE103",
                    "CE119",
                    "CE125",
                    "CE124",
                    "CE118",
                    "CE213",
                    "IT007",
                    "CE126",
                    "CE409",
                    "CE226",
                    "CE433",
                    "CE436",
                    "CE207",
                    "CE208",
                    "CE337",
                    "CE351",
                    "CE349",
                    "CE352",
                    "CE350",
                    "CE336",
                    "CE334",
                    "CE332",
                    "CE353",
                    "CE434",
                    "CE435",
                    "SS004",
                    "INI01",
                    "CE502",
                    "CE505",
                    "CE507",
                    "CE508",
                    "CE512"
                ],
                "progress_details": {
                    "required_general_education": 56,
                    "required_major_core": 12,
                    "required_major_foundation": 46,
                    "required_graduation_project": 12,
                    "required_elective_credits": 6
                }
            }
        ]
    }
]